proven/__init__.py
proven/core.py
proven/py.typed
proven/safe_crypto.py
proven/safe_currency.py
proven/safe_email.py
proven/safe_hex.py
proven/safe_math.py
proven/safe_network.py
proven/safe_path.py
proven/safe_phone.py
proven/safe_string.py
proven/safe_url.py
proven/safe_uuid.py
proven-0.9.0.dist-info/METADATA
proven-0.9.0.dist-info/WHEEL
proven-0.9.0.dist-info/top_level.txt
proven-0.9.0.dist-info/RECORD
