Metadata-Version: 2.4
Name: proven
Version: 0.9.0
Summary: Code that cannot crash - verified safety functions from Idris 2
Author-email: Hyperpolymath <hyperpolymath@proton.me>
License: PMPL-1.0
Project-URL: Homepage, https://github.com/hyperpolymath/proven
Project-URL: Repository, https://github.com/hyperpolymath/proven
Project-URL: Documentation, https://github.com/hyperpolymath/proven#readme
Keywords: safety,verified,idris,ffi,crash-free
Classifier: Development Status :: 3 - Alpha
Classifier: Intended Audience :: Developers
Classifier: Topic :: Software Development :: Libraries
Classifier: Programming Language :: Python :: 3
Classifier: Programming Language :: Python :: 3.9
Classifier: Programming Language :: Python :: 3.10
Classifier: Programming Language :: Python :: 3.11
Classifier: Programming Language :: Python :: 3.12
Classifier: Typing :: Typed
Requires-Python: >=3.9
